{"final_prose":{"paragraphs":[],"pass_number":0,"prose_hash":"","prose_id":"","skeleton_id":"","total_sentence_count":0,"total_word_count":0},"gate_result":{"first_failure":null,"gate_results":[],"total_violations":0,"verdict":"FAIL"},"oracle_result":{"combined_score":0,"first_failure":null,"oracle_results":[],"total_violations":0,"verdict":"FAIL","weakest_oracle":null},"output_hash":"","output_id":"","plan_hash":"","plan_id":"","rewrite_history":{"accepted_pass":0,"candidates":[],"rewrite_hash":"","total_passes":0},"segment_to_paragraph_map":{},"skeleton_hash":""}